main.py
aws_services/__init__.py
aws_services/api_gateway/__init__.py
aws_services/api_gateway/api_gateway_constants.py
aws_services/api_gateway/api_gateway_service.py
aws_services/dat_lambda/__init__.py
aws_services/dat_lambda/lambda_constants.py
aws_services/dat_lambda/lambda_service.py
aws_services/dynamodb/__init__.py
aws_services/dynamodb/dynamodb_constants.py
aws_services/dynamodb/dynamodb_service.py
aws_services/kinesis_stream/__init__.py
aws_services/kinesis_stream/kinesis_stream_constants.py
aws_services/kinesis_stream/kinesis_stream_service.py
aws_services/redshift/__init__.py
aws_services/redshift/redshift_constants.py
aws_services/redshift/redshift_service.py
aws_services/s3/__init__.py
aws_services/s3/s3_constants.py
aws_services/s3/s3_service.py
aws_services/sns/__init__.py
aws_services/sns/sns_constants.py
aws_services/sns/sns_service.py
aws_services/sqs/__init__.py
aws_services/sqs/sqs_constants.py
aws_services/sqs/sqs_service.py
common/__init__.py
common/constants/__init__.py
common/constants/application_constants.py
common/templates/audit_report.html
common/templates/index.html
dna_audit_new-0.1.dist-info/METADATA
dna_audit_new-0.1.dist-info/WHEEL
dna_audit_new-0.1.dist-info/entry_points.txt
dna_audit_new-0.1.dist-info/top_level.txt
dna_audit_new-0.1.dist-info/RECORD
